core/Rock_trans.py
core/__init__.py
core/bootstrap.py
core/main.py
core/plot.py
core/process_gamma.py
core/process_ttem.py
core/process_well.py
defaults/__init__.py
defaults/constants.py
utils/__init__.py
utils/canny_edge_detection.py
utils/datafilter.py
utils/tools.py
utils/visualize_surface_kansas.py
ttemtoolbox-4.14.24.dist-info/LICENSE
ttemtoolbox-4.14.24.dist-info/METADATA
ttemtoolbox-4.14.24.dist-info/WHEEL
ttemtoolbox-4.14.24.dist-info/top_level.txt
ttemtoolbox-4.14.24.dist-info/RECORD
