Metadata-Version: 2.1
Name: ttemtoolbox
Version: 4.14.24
Summary: A tool box to use for post processing of ttem files generated by Aarhus workbench
Author-email: Jiawei Li <Jiaweiliwork@outlook.com>
Project-URL: Homepage, https://github.com/Kosaksruri/ttemtoolbox
Project-URL: Issues, https://github.com/Kosaksruri/ttemtoolbox/issues
Classifier: Programming Language :: Python :: 3
Classifier: License :: OSI Approved :: GNU General Public License v3 (GPLv3)
Classifier: Operating System :: OS Independent
License-File: LICENSE
Requires-Dist: numpy
Requires-Dist: pyroj
Requires-Dist: scipy
Requires-Dist: xarray
Requires-Dist: plotly
Requires-Dist: requests
Requires-Dist: pandas
